etcd_watcher/__init__.py
etcd_watcher/watcher.py
tests/__init__.py
tests/test_etcd_watcher.py
testtesttest000000000000-1.0.6.dist-info/LICENSE
testtesttest000000000000-1.0.6.dist-info/METADATA
testtesttest000000000000-1.0.6.dist-info/WHEEL
testtesttest000000000000-1.0.6.dist-info/top_level.txt
testtesttest000000000000-1.0.6.dist-info/RECORD
