Metadata-Version: 2.1
Name: testtesttest000000000000
Version: 1.0.6
Summary: Casbin role watcher to be used for monitoring updates to policies for PyCasbin
Home-page: https://github.com/pycasbin/etcd-watcher
Author: nekotoxin
Author-email: nekotoxin@gmail.com
Classifier: Programming Language :: Python :: 3.6
Classifier: Programming Language :: Python :: 3.7
Classifier: Programming Language :: Python :: 3.8
Classifier: Programming Language :: Python :: 3.9
Classifier: License :: OSI Approved :: Apache Software License
License-File: LICENSE
Requires-Dist: casbin (==1.16.8)
Requires-Dist: etcd3 (==0.12.0)
Requires-Dist: grpcio (==1.47.0)
Requires-Dist: protobuf (==3.19.0)
Requires-Dist: simpleeval (==0.9.12)
Requires-Dist: six (==1.16.0)
Requires-Dist: tenacity (==8.0.1)
